breachsearch/__init__.py
breachsearch/main.py
breachsearch-2.1.1.dist-info/METADATA
breachsearch-2.1.1.dist-info/WHEEL
breachsearch-2.1.1.dist-info/entry_points.txt
breachsearch-2.1.1.dist-info/top_level.txt
breachsearch-2.1.1.dist-info/RECORD
